gocardless_pro/__init__.py
gocardless_pro/api_client.py
gocardless_pro/api_response.py
gocardless_pro/client.py
gocardless_pro/errors.py
gocardless_pro/list_response.py
gocardless_pro/paginator.py
gocardless_pro/rate_limit.py
gocardless_pro/webhooks.py
gocardless_pro/resources/__init__.py
gocardless_pro/resources/balance.py
gocardless_pro/resources/bank_account_detail.py
gocardless_pro/resources/bank_authorisation.py
gocardless_pro/resources/bank_details_lookup.py
gocardless_pro/resources/billing_request.py
gocardless_pro/resources/billing_request_flow.py
gocardless_pro/resources/billing_request_template.py
gocardless_pro/resources/billing_request_with_action.py
gocardless_pro/resources/block.py
gocardless_pro/resources/creditor.py
gocardless_pro/resources/creditor_bank_account.py
gocardless_pro/resources/currency_exchange_rate.py
gocardless_pro/resources/customer.py
gocardless_pro/resources/customer_bank_account.py
gocardless_pro/resources/customer_notification.py
gocardless_pro/resources/event.py
gocardless_pro/resources/export.py
gocardless_pro/resources/instalment_schedule.py
gocardless_pro/resources/institution.py
gocardless_pro/resources/logo.py
gocardless_pro/resources/mandate.py
gocardless_pro/resources/mandate_import.py
gocardless_pro/resources/mandate_import_entry.py
gocardless_pro/resources/mandate_pdf.py
gocardless_pro/resources/negative_balance_limit.py
gocardless_pro/resources/outbound_payment.py
gocardless_pro/resources/payer_authorisation.py
gocardless_pro/resources/payer_theme.py
gocardless_pro/resources/payment.py
gocardless_pro/resources/payout.py
gocardless_pro/resources/payout_item.py
gocardless_pro/resources/redirect_flow.py
gocardless_pro/resources/refund.py
gocardless_pro/resources/scenario_simulator.py
gocardless_pro/resources/scheme_identifier.py
gocardless_pro/resources/subscription.py
gocardless_pro/resources/tax_rate.py
gocardless_pro/resources/transferred_mandate.py
gocardless_pro/resources/verification_detail.py
gocardless_pro-3.2.0.dist-info/licenses/LICENSE
gocardless_pro-3.2.0.dist-info/METADATA
gocardless_pro-3.2.0.dist-info/WHEEL
gocardless_pro-3.2.0.dist-info/top_level.txt
gocardless_pro-3.2.0.dist-info/RECORD
