Metadata-Version: 2.4
Name: gocardless_pro
Version: 3.2.0
Summary: A client library for the GoCardless Pro API.
Home-page: https://github.com/gocardless/gocardless-pro-python
Author: GoCardless
Author-email: engineering@gocardless.com
License: MIT
Keywords: gocardless directdebit payments sepa bacs
License-File: LICENSE
Requires-Dist: requests>=2.6
Requires-Dist: six
Dynamic: author
Dynamic: author-email
Dynamic: description
Dynamic: home-page
Dynamic: keywords
Dynamic: license
Dynamic: license-file
Dynamic: requires-dist
Dynamic: summary
